msgraphlib/__init__.py
msgraphlib/common.py
msgraphlib/core.py
msgraphlib/drive.py
msgraphlib/excel.py
msgraphlib/files_old.py
msgraphlib/metadata.py
msgraphlib/sharepoint.py
msgraphlib/testmodule.py
msgraphlib-0.1.3.dist-info/LICENSE
msgraphlib-0.1.3.dist-info/METADATA
msgraphlib-0.1.3.dist-info/WHEEL
msgraphlib-0.1.3.dist-info/top_level.txt
msgraphlib-0.1.3.dist-info/RECORD
