Metadata-Version: 2.1
Name: msgraphlib
Version: 0.1.3
Summary: Microsoft Graph API Explorer
Author-email: Pawel Musial <pawel.r.musial@gmail.com>
Project-URL: Homepage, https://github.com/pypa/sampleproject
Project-URL: Bug Tracker, https://github.com/pypa/sampleproject/issues
Classifier: Programming Language :: Python :: 3
Classifier: License :: OSI Approved :: MIT License
Classifier: Operating System :: OS Independent
Requires-Python: >=3.10
License-File: LICENSE
Requires-Dist: requests (>=2.28.1)
Requires-Dist: msal (>=1.21.0)
